{"last_update": "17:28:10", "fleet": {"TRX/USDT": {"price": 0.3468, "position": "LONG", "roi": 13.16957679786922, "pnl_max": 2.8410772417875108, "breakeven": true}, "MANA/USDT": {"price": 0.0925, "position": "LONG", "roi": 10.48565121412803, "pnl_max": 3.8631346578366483, "breakeven": true}}, "mode": "CROSS_MARGIN", "energy_ranking": [{"symbol": "IOTX/USDT", "score": 2.53}, {"symbol": "FET/USDT", "score": 2.2}, {"symbol": "AXS/USDT", "score": 1.9}, {"symbol": "AVAX/USDT", "score": 1.85}, {"symbol": "HOT/USDT", "score": 1.79}, {"symbol": "GRT/USDT", "score": 1.78}, {"symbol": "CHZ/USDT", "score": 1.74}, {"symbol": "MANA/USDT", "score": 1.68}, {"symbol": "NEAR/USDT", "score": 1.66}, {"symbol": "BNB/USDT", "score": 1.6}, {"symbol": "CAKE/USDT", "score": 1.5}, {"symbol": "ATOM/USDT", "score": 1.44}, {"symbol": "ONE/USDT", "score": 1.33}, {"symbol": "LINK/USDT", "score": 1.32}, {"symbol": "ZRX/USDT", "score": 1.29}, {"symbol": "SOL/USDT", "score": 1.27}, {"symbol": "DOT/USDT", "score": 1.14}, {"symbol": "GALA/USDT", "score": 1.14}, {"symbol": "ALGO/USDT", "score": 1.13}, {"symbol": "SHIB/USDT", "score": 1.12}, {"symbol": "TRX/USDT", "score": 1.12}, {"symbol": "BCH/USDT", "score": 1.11}, {"symbol": "VET/USDT", "score": 1.03}, {"symbol": "XRP/USDT", "score": 0.99}, {"symbol": "ETC/USDT", "score": 0.99}, {"symbol": "BTC/USDT", "score": 0.98}, {"symbol": "ANKR/USDT", "score": 0.92}, {"symbol": "HBAR/USDT", "score": 0.88}, {"symbol": "CRV/USDT", "score": 0.86}, {"symbol": "EGLD/USDT", "score": 0.83}, {"symbol": "STX/USDT", "score": 0.83}, {"symbol": "SAND/USDT", "score": 0.77}, {"symbol": "ZIL/USDT", "score": 0.72}, {"symbol": "ADA/USDT", "score": 0.7}, {"symbol": "ENJ/USDT", "score": 0.69}, {"symbol": "AAVE/USDT", "score": 0.54}, {"symbol": "DOGE/USDT", "score": 0.45}, {"symbol": "ICP/USDT", "score": 0.32}, {"symbol": "FIL/USDT", "score": 0.31}, {"symbol": "RVN/USDT", "score": 0.25}, {"symbol": "ETH/USDT", "score": 0.16}, {"symbol": "BAT/USDT", "score": 0.16}, {"symbol": "LTC/USDT", "score": 0.15}, {"symbol": "KAVA/USDT", "score": 0.12}, {"symbol": "FLOW/USDT", "score": 0.1}, {"symbol": "THETA/USDT", "score": 0.09}]}