{"last_update": "07:40:12", "fleet": {}, "mode": "CROSS_MARGIN", "energy_ranking": [{"symbol": "KAVA/USDT", "score": 5.81}, {"symbol": "ETC/USDT", "score": 2.41}, {"symbol": "GALA/USDT", "score": 2.01}, {"symbol": "BTC/USDT", "score": 2.0}, {"symbol": "ENJ/USDT", "score": 1.72}, {"symbol": "ATOM/USDT", "score": 1.63}, {"symbol": "ICP/USDT", "score": 1.51}, {"symbol": "LTC/USDT", "score": 1.31}, {"symbol": "ONE/USDT", "score": 1.16}, {"symbol": "ADA/USDT", "score": 1.07}, {"symbol": "AVAX/USDT", "score": 1.07}, {"symbol": "CRV/USDT", "score": 0.9}, {"symbol": "BCH/USDT", "score": 0.74}, {"symbol": "AXS/USDT", "score": 0.7}, {"symbol": "AAVE/USDT", "score": 0.62}, {"symbol": "STX/USDT", "score": 0.6}, {"symbol": "ETH/USDT", "score": 0.59}, {"symbol": "LINK/USDT", "score": 0.59}, {"symbol": "FIL/USDT", "score": 0.59}, {"symbol": "ZIL/USDT", "score": 0.57}, {"symbol": "FET/USDT", "score": 0.55}, {"symbol": "XRP/USDT", "score": 0.54}, {"symbol": "DOGE/USDT", "score": 0.53}, {"symbol": "VET/USDT", "score": 0.53}, {"symbol": "HOT/USDT", "score": 0.53}, {"symbol": "ZRX/USDT", "score": 0.53}, {"symbol": "CHZ/USDT", "score": 0.4}, {"symbol": "HBAR/USDT", "score": 0.39}, {"symbol": "DOT/USDT", "score": 0.38}, {"symbol": "SAND/USDT", "score": 0.37}, {"symbol": "GRT/USDT", "score": 0.36}, {"symbol": "EGLD/USDT", "score": 0.29}, {"symbol": "BNB/USDT", "score": 0.25}, {"symbol": "ALGO/USDT", "score": 0.25}, {"symbol": "SOL/USDT", "score": 0.22}, {"symbol": "RVN/USDT", "score": 0.21}, {"symbol": "IOTX/USDT", "score": 0.21}, {"symbol": "NEAR/USDT", "score": 0.18}, {"symbol": "SHIB/USDT", "score": 0.16}, {"symbol": "TRX/USDT", "score": 0.13}, {"symbol": "FLOW/USDT", "score": 0.13}, {"symbol": "THETA/USDT", "score": 0.11}, {"symbol": "BAT/USDT", "score": 0.05}, {"symbol": "ANKR/USDT", "score": 0.05}, {"symbol": "MANA/USDT", "score": 0.01}, {"symbol": "CAKE/USDT", "score": 0.0}]}