{"last_update": "06:41:28", "fleet": {"TRX/USDT": {"price": 0.3418, "position": "LONG", "roi": 5.770938147380904, "pnl_max": 1.213376738680097, "breakeven": true}}, "mode": "CROSS_MARGIN", "energy_ranking": [{"symbol": "LINK/USDT", "score": 2.76}, {"symbol": "FLOW/USDT", "score": 2.62}, {"symbol": "ETC/USDT", "score": 2.47}, {"symbol": "KAVA/USDT", "score": 2.09}, {"symbol": "MANA/USDT", "score": 1.9}, {"symbol": "AXS/USDT", "score": 1.74}, {"symbol": "AVAX/USDT", "score": 1.72}, {"symbol": "BNB/USDT", "score": 1.61}, {"symbol": "RVN/USDT", "score": 1.4}, {"symbol": "ONE/USDT", "score": 1.35}, {"symbol": "CAKE/USDT", "score": 0.95}, {"symbol": "ENJ/USDT", "score": 0.91}, {"symbol": "ZIL/USDT", "score": 0.88}, {"symbol": "BTC/USDT", "score": 0.78}, {"symbol": "CRV/USDT", "score": 0.76}, {"symbol": "GALA/USDT", "score": 0.67}, {"symbol": "SHIB/USDT", "score": 0.65}, {"symbol": "ETH/USDT", "score": 0.63}, {"symbol": "DOT/USDT", "score": 0.63}, {"symbol": "STX/USDT", "score": 0.61}, {"symbol": "DOGE/USDT", "score": 0.56}, {"symbol": "ALGO/USDT", "score": 0.52}, {"symbol": "ADA/USDT", "score": 0.5}, {"symbol": "SOL/USDT", "score": 0.44}, {"symbol": "SAND/USDT", "score": 0.43}, {"symbol": "XRP/USDT", "score": 0.42}, {"symbol": "LTC/USDT", "score": 0.38}, {"symbol": "HOT/USDT", "score": 0.35}, {"symbol": "ZRX/USDT", "score": 0.34}, {"symbol": "GRT/USDT", "score": 0.3}, {"symbol": "BCH/USDT", "score": 0.28}, {"symbol": "ANKR/USDT", "score": 0.25}, {"symbol": "FET/USDT", "score": 0.23}, {"symbol": "FIL/USDT", "score": 0.22}, {"symbol": "NEAR/USDT", "score": 0.18}, {"symbol": "TRX/USDT", "score": 0.18}, {"symbol": "ICP/USDT", "score": 0.15}, {"symbol": "CHZ/USDT", "score": 0.14}, {"symbol": "ATOM/USDT", "score": 0.13}, {"symbol": "HBAR/USDT", "score": 0.13}, {"symbol": "EGLD/USDT", "score": 0.08}, {"symbol": "VET/USDT", "score": 0.06}, {"symbol": "IOTX/USDT", "score": 0.06}, {"symbol": "THETA/USDT", "score": 0.03}, {"symbol": "BAT/USDT", "score": 0.03}, {"symbol": "AAVE/USDT", "score": 0.01}]}