{"last_update": "07:21:45", "fleet": {}, "mode": "CROSS_MARGIN", "energy_ranking": [{"symbol": "ADA/USDT", "score": 9.03}, {"symbol": "LINK/USDT", "score": 8.51}, {"symbol": "SOL/USDT", "score": 7.48}, {"symbol": "FET/USDT", "score": 6.23}, {"symbol": "ETH/USDT", "score": 5.42}, {"symbol": "AVAX/USDT", "score": 4.65}, {"symbol": "AAVE/USDT", "score": 4.52}, {"symbol": "DOGE/USDT", "score": 3.63}, {"symbol": "HBAR/USDT", "score": 3.6}, {"symbol": "FIL/USDT", "score": 3.54}, {"symbol": "GRT/USDT", "score": 3.48}, {"symbol": "STX/USDT", "score": 3.3}, {"symbol": "CRV/USDT", "score": 3.11}, {"symbol": "XRP/USDT", "score": 2.34}, {"symbol": "CAKE/USDT", "score": 2.31}, {"symbol": "SHIB/USDT", "score": 2.27}, {"symbol": "BTC/USDT", "score": 2.05}, {"symbol": "ETC/USDT", "score": 1.76}, {"symbol": "ICP/USDT", "score": 1.47}, {"symbol": "DOT/USDT", "score": 1.17}, {"symbol": "VET/USDT", "score": 1.09}, {"symbol": "ZIL/USDT", "score": 1.09}, {"symbol": "KAVA/USDT", "score": 1.04}, {"symbol": "EGLD/USDT", "score": 0.99}, {"symbol": "ZRX/USDT", "score": 0.97}, {"symbol": "SAND/USDT", "score": 0.92}, {"symbol": "ALGO/USDT", "score": 0.64}, {"symbol": "TRX/USDT", "score": 0.6}, {"symbol": "CHZ/USDT", "score": 0.55}, {"symbol": "ONE/USDT", "score": 0.52}, {"symbol": "ATOM/USDT", "score": 0.51}, {"symbol": "RVN/USDT", "score": 0.37}, {"symbol": "BCH/USDT", "score": 0.36}, {"symbol": "HOT/USDT", "score": 0.36}, {"symbol": "LTC/USDT", "score": 0.35}, {"symbol": "AXS/USDT", "score": 0.33}, {"symbol": "BNB/USDT", "score": 0.28}, {"symbol": "ANKR/USDT", "score": 0.26}, {"symbol": "MANA/USDT", "score": 0.23}, {"symbol": "BAT/USDT", "score": 0.15}, {"symbol": "NEAR/USDT", "score": 0.06}, {"symbol": "ENJ/USDT", "score": 0.06}, {"symbol": "GALA/USDT", "score": 0.05}, {"symbol": "IOTX/USDT", "score": 0.03}, {"symbol": "THETA/USDT", "score": 0.0}, {"symbol": "FLOW/USDT", "score": 0.0}]}