{"last_update": "21:05:45", "fleet": {"TRX/USDT": {"price": 0.3486, "position": "LONG", "roi": 15.833086712045047, "pnl_max": 3.344184670020726, "breakeven": true}, "MANA/USDT": {"price": 0.0914, "position": "LONG", "roi": 4.4150110375275675, "pnl_max": 3.8631346578366483, "breakeven": true}}, "mode": "CROSS_MARGIN", "energy_ranking": [{"symbol": "LTC/USDT", "score": 2.61}, {"symbol": "IOTX/USDT", "score": 2.36}, {"symbol": "GALA/USDT", "score": 2.32}, {"symbol": "ADA/USDT", "score": 2.25}, {"symbol": "GRT/USDT", "score": 2.24}, {"symbol": "SOL/USDT", "score": 2.14}, {"symbol": "AXS/USDT", "score": 2.07}, {"symbol": "SAND/USDT", "score": 1.97}, {"symbol": "FET/USDT", "score": 1.86}, {"symbol": "AVAX/USDT", "score": 1.81}, {"symbol": "ICP/USDT", "score": 1.81}, {"symbol": "HBAR/USDT", "score": 1.78}, {"symbol": "ONE/USDT", "score": 1.73}, {"symbol": "BCH/USDT", "score": 1.67}, {"symbol": "CHZ/USDT", "score": 1.67}, {"symbol": "BNB/USDT", "score": 1.65}, {"symbol": "DOT/USDT", "score": 1.63}, {"symbol": "CRV/USDT", "score": 1.61}, {"symbol": "MANA/USDT", "score": 1.6}, {"symbol": "ETH/USDT", "score": 1.59}, {"symbol": "LINK/USDT", "score": 1.56}, {"symbol": "FIL/USDT", "score": 1.52}, {"symbol": "HOT/USDT", "score": 1.44}, {"symbol": "CAKE/USDT", "score": 1.43}, {"symbol": "RVN/USDT", "score": 1.35}, {"symbol": "ETC/USDT", "score": 1.25}, {"symbol": "SHIB/USDT", "score": 1.17}, {"symbol": "EGLD/USDT", "score": 1.17}, {"symbol": "ZRX/USDT", "score": 1.01}, {"symbol": "TRX/USDT", "score": 0.9}, {"symbol": "STX/USDT", "score": 0.83}, {"symbol": "BTC/USDT", "score": 0.67}, {"symbol": "VET/USDT", "score": 0.64}, {"symbol": "DOGE/USDT", "score": 0.62}, {"symbol": "ATOM/USDT", "score": 0.6}, {"symbol": "ZIL/USDT", "score": 0.56}, {"symbol": "ALGO/USDT", "score": 0.51}, {"symbol": "ENJ/USDT", "score": 0.51}, {"symbol": "NEAR/USDT", "score": 0.48}, {"symbol": "AAVE/USDT", "score": 0.48}, {"symbol": "ANKR/USDT", "score": 0.45}, {"symbol": "XRP/USDT", "score": 0.37}, {"symbol": "BAT/USDT", "score": 0.31}, {"symbol": "FLOW/USDT", "score": 0.24}, {"symbol": "THETA/USDT", "score": 0.15}, {"symbol": "KAVA/USDT", "score": 0.07}]}