{"last_update": "00:25:32", "fleet": {}, "mode": "CROSS_MARGIN", "energy_ranking": [{"symbol": "TRX/USDT", "score": 2.85}, {"symbol": "FLOW/USDT", "score": 2.77}, {"symbol": "BCH/USDT", "score": 2.61}, {"symbol": "HOT/USDT", "score": 2.41}, {"symbol": "CAKE/USDT", "score": 2.26}, {"symbol": "ATOM/USDT", "score": 1.9}, {"symbol": "DOGE/USDT", "score": 1.05}, {"symbol": "EGLD/USDT", "score": 0.99}, {"symbol": "AAVE/USDT", "score": 0.97}, {"symbol": "GRT/USDT", "score": 0.9}, {"symbol": "CHZ/USDT", "score": 0.9}, {"symbol": "AXS/USDT", "score": 0.85}, {"symbol": "CRV/USDT", "score": 0.67}, {"symbol": "BNB/USDT", "score": 0.66}, {"symbol": "VET/USDT", "score": 0.55}, {"symbol": "NEAR/USDT", "score": 0.52}, {"symbol": "XRP/USDT", "score": 0.49}, {"symbol": "BAT/USDT", "score": 0.47}, {"symbol": "ETC/USDT", "score": 0.44}, {"symbol": "IOTX/USDT", "score": 0.39}, {"symbol": "MANA/USDT", "score": 0.38}, {"symbol": "FET/USDT", "score": 0.37}, {"symbol": "ZIL/USDT", "score": 0.34}, {"symbol": "STX/USDT", "score": 0.32}, {"symbol": "ICP/USDT", "score": 0.28}, {"symbol": "BTC/USDT", "score": 0.25}, {"symbol": "ADA/USDT", "score": 0.25}, {"symbol": "THETA/USDT", "score": 0.25}, {"symbol": "SHIB/USDT", "score": 0.21}, {"symbol": "ONE/USDT", "score": 0.2}, {"symbol": "RVN/USDT", "score": 0.17}, {"symbol": "ALGO/USDT", "score": 0.14}, {"symbol": "ZRX/USDT", "score": 0.14}, {"symbol": "GALA/USDT", "score": 0.12}, {"symbol": "FIL/USDT", "score": 0.11}, {"symbol": "DOT/USDT", "score": 0.1}, {"symbol": "AVAX/USDT", "score": 0.1}, {"symbol": "ENJ/USDT", "score": 0.1}, {"symbol": "ANKR/USDT", "score": 0.09}, {"symbol": "SOL/USDT", "score": 0.08}, {"symbol": "LINK/USDT", "score": 0.08}, {"symbol": "KAVA/USDT", "score": 0.08}, {"symbol": "ETH/USDT", "score": 0.07}, {"symbol": "HBAR/USDT", "score": 0.07}, {"symbol": "SAND/USDT", "score": 0.04}, {"symbol": "LTC/USDT", "score": 0.01}]}