{"last_update": "13:14:44", "fleet": {"TRX/USDT": {"price": 0.3408, "position": "LONG", "roi": 4.29121041728324, "pnl_max": 1.213376738680097, "breakeven": true}}, "mode": "CROSS_MARGIN", "energy_ranking": [{"symbol": "ADA/USDT", "score": 6.54}, {"symbol": "ANKR/USDT", "score": 5.94}, {"symbol": "LINK/USDT", "score": 5.41}, {"symbol": "AVAX/USDT", "score": 4.57}, {"symbol": "ZIL/USDT", "score": 4.37}, {"symbol": "ICP/USDT", "score": 3.84}, {"symbol": "ALGO/USDT", "score": 3.71}, {"symbol": "DOT/USDT", "score": 3.39}, {"symbol": "SAND/USDT", "score": 2.76}, {"symbol": "STX/USDT", "score": 2.44}, {"symbol": "FIL/USDT", "score": 2.4}, {"symbol": "BAT/USDT", "score": 2.32}, {"symbol": "AXS/USDT", "score": 1.98}, {"symbol": "IOTX/USDT", "score": 1.54}, {"symbol": "MANA/USDT", "score": 1.52}, {"symbol": "KAVA/USDT", "score": 1.32}, {"symbol": "ATOM/USDT", "score": 1.27}, {"symbol": "CRV/USDT", "score": 1.24}, {"symbol": "RVN/USDT", "score": 1.2}, {"symbol": "VET/USDT", "score": 1.14}, {"symbol": "HBAR/USDT", "score": 1.01}, {"symbol": "ZRX/USDT", "score": 0.97}, {"symbol": "EGLD/USDT", "score": 0.89}, {"symbol": "BNB/USDT", "score": 0.85}, {"symbol": "FET/USDT", "score": 0.71}, {"symbol": "SOL/USDT", "score": 0.68}, {"symbol": "NEAR/USDT", "score": 0.65}, {"symbol": "CHZ/USDT", "score": 0.62}, {"symbol": "SHIB/USDT", "score": 0.6}, {"symbol": "GRT/USDT", "score": 0.6}, {"symbol": "FLOW/USDT", "score": 0.58}, {"symbol": "BTC/USDT", "score": 0.55}, {"symbol": "CAKE/USDT", "score": 0.33}, {"symbol": "BCH/USDT", "score": 0.32}, {"symbol": "LTC/USDT", "score": 0.27}, {"symbol": "ETH/USDT", "score": 0.22}, {"symbol": "GALA/USDT", "score": 0.21}, {"symbol": "XRP/USDT", "score": 0.2}, {"symbol": "AAVE/USDT", "score": 0.2}, {"symbol": "ENJ/USDT", "score": 0.2}, {"symbol": "ETC/USDT", "score": 0.18}, {"symbol": "ONE/USDT", "score": 0.12}, {"symbol": "HOT/USDT", "score": 0.11}, {"symbol": "DOGE/USDT", "score": 0.09}, {"symbol": "TRX/USDT", "score": 0.06}, {"symbol": "THETA/USDT", "score": 0.03}]}