{"last_update": "07:38:21", "fleet": {}, "mode": "CROSS_MARGIN", "energy_ranking": [{"symbol": "SOL/USDT", "score": 3.36}, {"symbol": "FET/USDT", "score": 3.25}, {"symbol": "BAT/USDT", "score": 2.88}, {"symbol": "RVN/USDT", "score": 2.79}, {"symbol": "IOTX/USDT", "score": 2.53}, {"symbol": "ANKR/USDT", "score": 2.16}, {"symbol": "HBAR/USDT", "score": 1.81}, {"symbol": "XRP/USDT", "score": 1.79}, {"symbol": "FIL/USDT", "score": 1.25}, {"symbol": "GRT/USDT", "score": 1.2}, {"symbol": "NEAR/USDT", "score": 1.03}, {"symbol": "VET/USDT", "score": 0.98}, {"symbol": "MANA/USDT", "score": 0.97}, {"symbol": "GALA/USDT", "score": 0.93}, {"symbol": "STX/USDT", "score": 0.93}, {"symbol": "AVAX/USDT", "score": 0.91}, {"symbol": "THETA/USDT", "score": 0.86}, {"symbol": "SAND/USDT", "score": 0.85}, {"symbol": "ZIL/USDT", "score": 0.83}, {"symbol": "EGLD/USDT", "score": 0.82}, {"symbol": "ADA/USDT", "score": 0.8}, {"symbol": "LTC/USDT", "score": 0.77}, {"symbol": "AAVE/USDT", "score": 0.66}, {"symbol": "FLOW/USDT", "score": 0.66}, {"symbol": "LINK/USDT", "score": 0.64}, {"symbol": "BTC/USDT", "score": 0.61}, {"symbol": "ONE/USDT", "score": 0.56}, {"symbol": "ENJ/USDT", "score": 0.54}, {"symbol": "ETH/USDT", "score": 0.43}, {"symbol": "DOGE/USDT", "score": 0.43}, {"symbol": "ETC/USDT", "score": 0.43}, {"symbol": "ATOM/USDT", "score": 0.38}, {"symbol": "ZRX/USDT", "score": 0.36}, {"symbol": "BNB/USDT", "score": 0.24}, {"symbol": "SHIB/USDT", "score": 0.22}, {"symbol": "CHZ/USDT", "score": 0.2}, {"symbol": "HOT/USDT", "score": 0.18}, {"symbol": "ICP/USDT", "score": 0.17}, {"symbol": "ALGO/USDT", "score": 0.14}, {"symbol": "BCH/USDT", "score": 0.12}, {"symbol": "DOT/USDT", "score": 0.05}, {"symbol": "CRV/USDT", "score": 0.03}, {"symbol": "AXS/USDT", "score": 0.02}, {"symbol": "CAKE/USDT", "score": 0.01}, {"symbol": "KAVA/USDT", "score": 0.01}, {"symbol": "TRX/USDT", "score": 0.0}]}