{"last_update": "20:15:09", "fleet": {}, "mode": "CROSS_MARGIN", "energy_ranking": [{"symbol": "FLOW/USDT", "score": 3.55}, {"symbol": "CAKE/USDT", "score": 2.38}, {"symbol": "BCH/USDT", "score": 2.15}, {"symbol": "ANKR/USDT", "score": 2.08}, {"symbol": "ATOM/USDT", "score": 1.49}, {"symbol": "GALA/USDT", "score": 1.37}, {"symbol": "SAND/USDT", "score": 1.36}, {"symbol": "BTC/USDT", "score": 1.2}, {"symbol": "TRX/USDT", "score": 0.92}, {"symbol": "AXS/USDT", "score": 0.92}, {"symbol": "GRT/USDT", "score": 0.87}, {"symbol": "AAVE/USDT", "score": 0.86}, {"symbol": "NEAR/USDT", "score": 0.81}, {"symbol": "IOTX/USDT", "score": 0.79}, {"symbol": "ZIL/USDT", "score": 0.75}, {"symbol": "STX/USDT", "score": 0.64}, {"symbol": "ZRX/USDT", "score": 0.63}, {"symbol": "ENJ/USDT", "score": 0.58}, {"symbol": "SOL/USDT", "score": 0.57}, {"symbol": "DOT/USDT", "score": 0.51}, {"symbol": "HBAR/USDT", "score": 0.51}, {"symbol": "ETH/USDT", "score": 0.47}, {"symbol": "LINK/USDT", "score": 0.44}, {"symbol": "SHIB/USDT", "score": 0.4}, {"symbol": "KAVA/USDT", "score": 0.39}, {"symbol": "BAT/USDT", "score": 0.38}, {"symbol": "XRP/USDT", "score": 0.35}, {"symbol": "CHZ/USDT", "score": 0.33}, {"symbol": "VET/USDT", "score": 0.31}, {"symbol": "ONE/USDT", "score": 0.26}, {"symbol": "ALGO/USDT", "score": 0.24}, {"symbol": "ETC/USDT", "score": 0.23}, {"symbol": "CRV/USDT", "score": 0.2}, {"symbol": "THETA/USDT", "score": 0.19}, {"symbol": "FET/USDT", "score": 0.19}, {"symbol": "RVN/USDT", "score": 0.17}, {"symbol": "HOT/USDT", "score": 0.16}, {"symbol": "EGLD/USDT", "score": 0.14}, {"symbol": "AVAX/USDT", "score": 0.13}, {"symbol": "MANA/USDT", "score": 0.13}, {"symbol": "BNB/USDT", "score": 0.12}, {"symbol": "ICP/USDT", "score": 0.12}, {"symbol": "DOGE/USDT", "score": 0.07}, {"symbol": "FIL/USDT", "score": 0.06}, {"symbol": "ADA/USDT", "score": 0.05}, {"symbol": "LTC/USDT", "score": 0.02}]}